GetTss/GetTss.py
GetTss/__init__.py
GetTss-0.0.2.dist-info/LICENSE
GetTss-0.0.2.dist-info/METADATA
GetTss-0.0.2.dist-info/WHEEL
GetTss-0.0.2.dist-info/entry_points.txt
GetTss-0.0.2.dist-info/top_level.txt
GetTss-0.0.2.dist-info/RECORD
